pdocs/__init__.py
pdocs/_version.py
pdocs/api.py
pdocs/cli.py
pdocs/defaults.py
pdocs/doc.py
pdocs/extract.py
pdocs/html_helpers.py
pdocs/logo.py
pdocs/render.py
pdocs/static.py
pdocs/templates/LICENSE
pdocs/templates/README.md
pdocs/templates/css.mako
pdocs/templates/html_frame.mako
pdocs/templates/html_index.mako
pdocs/templates/html_module.mako
pdocs/templates/text.mako
tmp_fat_pdocs-1.2.1.dist-info/METADATA
tmp_fat_pdocs-1.2.1.dist-info/WHEEL
tmp_fat_pdocs-1.2.1.dist-info/licenses/LICENSE
tmp_fat_pdocs-1.2.1.dist-info/RECORD
