Metadata-Version: 2.4
Name: tmp-fat-pdocs
Version: 1.2.1
Summary: A simple program and library to auto generate API documentation for Python modules.
Author-email: Timothy Crosley <timothy.crosley@gmail.com>, "Phil Weir (fork)" <phil.weir@flaxandteal.co.uk>
License-Expression: MIT
License-File: LICENSE
Requires-Python: >=3.7
Requires-Dist: docstring-parser>=0.7.2
Requires-Dist: mako>1.2.2
Requires-Dist: markdown>=3.0.0
Provides-Extra: dev
Requires-Dist: bandit>=1.6; extra == 'dev'
Requires-Dist: black; extra == 'dev'
Requires-Dist: flake8-bugbear>=19.8; extra == 'dev'
Requires-Dist: flake8>=3.7; extra == 'dev'
Requires-Dist: ipython>=7.7; extra == 'dev'
Requires-Dist: isort>=4.3; extra == 'dev'
Requires-Dist: mypy>=0.720.0; extra == 'dev'
Requires-Dist: pep8-naming>=0.8.2; extra == 'dev'
Requires-Dist: pytest-cov>=2.7; extra == 'dev'
Requires-Dist: pytest-mock>=1.10; extra == 'dev'
Requires-Dist: pytest>=5.1; extra == 'dev'
Requires-Dist: safety>=1.8; extra == 'dev'
Requires-Dist: types-markdown>0.0; extra == 'dev'
Requires-Dist: vulture>=1.0; extra == 'dev'
